vpnflow/__init__.py
vpnflow/__main__.py
vpnflow/bot/__init__.py
vpnflow/bot/base.py
vpnflow/bot/callbacks.py
vpnflow/bot/commands.py
vpnflow/bot/filters.py
vpnflow/bot/keyboards/__init__.py
vpnflow/bot/keyboards/inline.py
vpnflow/bot/middleware.py
vpnflow/bot/routers/__init__.py
vpnflow/bot/routers/admin.py
vpnflow/bot/routers/base.py
vpnflow/bot/routers/errors.py
vpnflow/bot/states.py
vpnflow/cli.py
vpnflow/db/__init__.py
vpnflow/db/base.py
vpnflow/db/events.py
vpnflow/db/models.py
vpnflow/db/repositories.py
vpnflow/db/tools.py
vpnflow/enums.py
vpnflow/flows/__init__.py
vpnflow/flows/_dagster.py
vpnflow/flows/_schedule.py
vpnflow/flows/base.py
vpnflow/log/__init__.py
vpnflow/log/telegram/__init__.py
vpnflow/log/telegram/formatters.py
vpnflow/log/telegram/handlers.py
vpnflow/misc.py
vpnflow/services/__init__.py
vpnflow/services/_cloudflare.py
vpnflow/services/_marzban.py
vpnflow/services/_redis.py
vpnflow/services/_telegram.py
vpnflow/services/business.py
vpnflow/services/cache.py
vpnflow/services/ssh.py
vpnflow/settings.py
vpnflow/web/__init__.py
vpnflow/web/app.py
vpnflow/web/schemas.py
vpnflow/web/views.py
vpnflow-1.1.0.dist-info/entry_points.txt
vpnflow-1.1.0.dist-info/LICENSE
vpnflow-1.1.0.dist-info/METADATA
vpnflow-1.1.0.dist-info/WHEEL
vpnflow-1.1.0.dist-info/RECORD
