Metadata-Version: 2.1
Name: vpnflow
Version: 1.1.0
Summary: VPN FLOW
License: AGPL
Keywords: vpn,flow
Author: Michael R. Kisel
Author-email: aioboy@yandex.com
Maintainer: Michael R. Kisel
Maintainer-email: aioboy@yandex.com
Requires-Python: >=3.8.1,<3.13
Classifier: Development Status :: 5 - Production/Stable
Classifier: License :: Other/Proprietary License
Classifier: Programming Language :: Python
Classifier: Programming Language :: Python :: 3
Classifier: Programming Language :: Python :: 3.9
Classifier: Programming Language :: Python :: 3.10
Classifier: Programming Language :: Python :: 3.11
Classifier: Programming Language :: Python :: 3.12
Classifier: Programming Language :: Python :: 3.8
Requires-Dist: Jinja2 (==3.1.5)
Requires-Dist: PyYAML (==6.0.2)
Requires-Dist: SQLAlchemy (==2.0.37)
Requires-Dist: aiocache (==0.12.3)
Requires-Dist: aiogram (==3.13.1)
Requires-Dist: alembic (==1.14.0)
Requires-Dist: asyncmy (==0.2.10)
Requires-Dist: asyncpg (==0.30.0)
Requires-Dist: bcrypt (==3.2.2)
Requires-Dist: cryptography (==42.0.8)
Requires-Dist: fastapi (==0.115.6)
Requires-Dist: paramiko (==3.5.0)
Requires-Dist: prometheus-fastapi-instrumentator (==7.0.0)
Requires-Dist: pydantic (==2.7.0)
Requires-Dist: pydantic-settings (==2.7.1)
Requires-Dist: redis (==5.2.1)
Requires-Dist: requests (==2.32.3)
Requires-Dist: schedule (==1.2.2)
Requires-Dist: uvicorn (==0.33.0)
Project-URL: homepage, https://pypi.org/project/vpnflow
